{
    "Eq. Guinea": [
        {
            "Eq. Guinea": [
                {
                    "id": 1,
                    "date": "2024-01-22T17:00:00Z",
                    "where": "A",
                    "result": "4:0",
                    "home_age": 27.818181818181817,
                    "away_age": 26.90909090909091
                }
            ]
        },
        {
            "Eq. Guinea": [
                {
                    "id": 1,
                    "date": "2022-01-12T19:00:00Z",
                    "where": "A",
                    "result": "0:1",
                    "home_age": 26.181818181818183,
                    "away_age": 29.0
                }
            ]
        }
    ]
}